{
  "informacion_personal": {
    "numero_identificacion": "1069489668",
    "nombres": "MARTIN ELIAS",
    "apellidos": "CALDERA CORONADO",
    "telefono": "3012090694",
    "departamento": "Córdoba",
    "institucion": "INDIVIDUAL (PAGO UNICO)"
  },
  "fecha": "7/2/2026 11:42:35",
  "puntajes": {
    "matemáticas": {
      "correctas": 18,
      "total_preguntas": 50,
      "porcentaje_real": 33.03,
      "puntaje": 30,
      "score_ponderado": 18,
      "peso_total": 54.5
    },
    "lectura crítica": {
      "correctas": 6,
      "total_preguntas": 41,
      "porcentaje_real": 15.0,
      "puntaje": 12,
      "score_ponderado": 7.5,
      "peso_total": 50.0
    },
    "sociales y ciudadanas": {
      "correctas": 8,
      "total_preguntas": 50,
      "porcentaje_real": 16.1,
      "puntaje": 14,
      "score_ponderado": 9.5,
      "peso_total": 59.0
    },
    "ciencias naturales": {
      "correctas": 21,
      "total_preguntas": 58,
      "porcentaje_real": 34.56,
      "puntaje": 31,
      "score_ponderado": 23.5,
      "peso_total": 68.0
    },
    "inglés": {
      "correctas": 19,
      "total_preguntas": 55,
      "porcentaje_real": 35.77,
      "puntaje": 31,
      "score_ponderado": 24.5,
      "peso_total": 68.5
    }
  },
  "respuestas_detalladas": {
    "matemáticas": {
      "1": {
        "respuesta": "B",
        "correcta": "B",
        "es_correcta": true
      },
      "2": {
        "respuesta": "C",
        "correcta": "B",
        "es_correcta": false
      },
      "3": {
        "respuesta": "D",
        "correcta": "D",
        "es_correcta": true
      },
      "4": {
        "respuesta": "B",
        "correcta": "B",
        "es_correcta": true
      },
      "5": {
        "respuesta": "A",
        "correcta": "A",
        "es_correcta": true
      },
      "6": {
        "respuesta": "A",
        "correcta": "A",
        "es_correcta": true
      },
      "7": {
        "respuesta": "B",
        "correcta": "B",
        "es_correcta": true
      },
      "8": {
        "respuesta": "A",
        "correcta": "B",
        "es_correcta": false
      },
      "9": {
        "respuesta": "C",
        "correcta": "A",
        "es_correcta": false
      },
      "10": {
        "respuesta": "C",
        "correcta": "C",
        "es_correcta": true
      },
      "11": {
        "respuesta": "A",
        "correcta": "D",
        "es_correcta": false
      },
      "12": {
        "respuesta": "B",
        "correcta": "B",
        "es_correcta": true
      },
      "13": {
        "respuesta": "B",
        "correcta": "B",
        "es_correcta": true
      },
      "14": {
        "respuesta": "D",
        "correcta": "D",
        "es_correcta": true
      },
      "15": {
        "respuesta": "C",
        "correcta": "C",
        "es_correcta": true
      },
      "16": {
        "respuesta": "B",
        "correcta": "C",
        "es_correcta": false
      },
      "17": {
        "respuesta": "D",
        "correcta": "D",
        "es_correcta": true
      },
      "18": {
        "respuesta": "B",
        "correcta": "C",
        "es_correcta": false
      },
      "19": {
        "respuesta": "D",
        "correcta": "C",
        "es_correcta": false
      },
      "20": {
        "respuesta": "C",
        "correcta": "C",
        "es_correcta": true
      },
      "21": {
        "respuesta": "B",
        "correcta": "A",
        "es_correcta": false
      },
      "22": {
        "respuesta": "B",
        "correcta": "B",
        "es_correcta": true
      },
      "23": {
        "respuesta": "A",
        "correcta": "B",
        "es_correcta": false
      },
      "24": {
        "respuesta": "A",
        "correcta": "B",
        "es_correcta": false
      },
      "25": {
        "respuesta": "A",
        "correcta": "C",
        "es_correcta": false
      },
      "26": {
        "respuesta": "B",
        "correcta": "B",
        "es_correcta": true
      },
      "27": {
        "respuesta": "B",
        "correcta": "A",
        "es_correcta": false
      },
      "28": {
        "respuesta": "A",
        "correcta": "C",
        "es_correcta": false
      },
      "29": {
        "respuesta": "D",
        "correcta": "C",
        "es_correcta": false
      },
      "30": {
        "respuesta": "C",
        "correcta": "A",
        "es_correcta": false
      },
      "31": {
        "respuesta": "A",
        "correcta": "D",
        "es_correcta": false
      },
      "32": {
        "respuesta": "B",
        "correcta": "C",
        "es_correcta": false
      },
      "33": {
        "respuesta": "D",
        "correcta": "C",
        "es_correcta": false
      },
      "34": {
        "respuesta": "C",
        "correcta": "A",
        "es_correcta": false
      },
      "35": {
        "respuesta": "C",
        "correcta": "C",
        "es_correcta": true
      },
      "36": {
        "respuesta": "B",
        "correcta": "B",
        "es_correcta": true
      },
      "37": {
        "respuesta": "D",
        "correcta": "B",
        "es_correcta": false
      },
      "38": {
        "respuesta": "A",
        "correcta": "C",
        "es_correcta": false
      },
      "39": {
        "respuesta": "A",
        "correcta": "C",
        "es_correcta": false
      },
      "40": {
        "respuesta": "A",
        "correcta": "C",
        "es_correcta": false
      },
      "41": {
        "respuesta": "B",
        "correcta": "C",
        "es_correcta": false
      },
      "42": {
        "respuesta": "C",
        "correcta": "D",
        "es_correcta": false
      },
      "43": {
        "respuesta": "A",
        "correcta": "C",
        "es_correcta": false
      },
      "44": {
        "respuesta": "A",
        "correcta": "C",
        "es_correcta": false
      },
      "45": {
        "respuesta": "D",
        "correcta": "C",
        "es_correcta": false
      },
      "46": {
        "respuesta": "C",
        "correcta": "C",
        "es_correcta": true
      },
      "47": {
        "respuesta": "B",
        "correcta": "A",
        "es_correcta": false
      },
      "48": {
        "respuesta": "A",
        "correcta": "B",
        "es_correcta": false
      },
      "49": {
        "respuesta": "D",
        "correcta": "B",
        "es_correcta": false
      },
      "50": {
        "respuesta": "D",
        "correcta": "A",
        "es_correcta": false
      }
    },
    "lectura crítica": {
      "26": {
        "respuesta": "A",
        "correcta": "D",
        "es_correcta": false
      },
      "27": {
        "respuesta": "B",
        "correcta": "B",
        "es_correcta": true
      },
      "28": {
        "respuesta": "C",
        "correcta": "B",
        "es_correcta": false
      },
      "29": {
        "respuesta": "D",
        "correcta": "B",
        "es_correcta": false
      },
      "30": {
        "respuesta": "A",
        "correcta": "B",
        "es_correcta": false
      },
      "31": {
        "respuesta": "C",
        "correcta": "D",
        "es_correcta": false
      },
      "32": {
        "respuesta": "B",
        "correcta": "C",
        "es_correcta": false
      },
      "33": {
        "respuesta": "A",
        "correcta": "C",
        "es_correcta": false
      },
      "34": {
        "respuesta": "A",
        "correcta": "B",
        "es_correcta": false
      },
      "35": {
        "respuesta": "B",
        "correcta": "C",
        "es_correcta": false
      },
      "36": {
        "respuesta": "C",
        "correcta": "C",
        "es_correcta": true
      },
      "37": {
        "respuesta": "C",
        "correcta": "D",
        "es_correcta": false
      },
      "38": {
        "respuesta": "D",
        "correcta": "C",
        "es_correcta": false
      },
      "39": {
        "respuesta": "A",
        "correcta": "C",
        "es_correcta": false
      },
      "40": {
        "respuesta": "B",
        "correcta": "A",
        "es_correcta": false
      },
      "41": {
        "respuesta": "A",
        "correcta": "B",
        "es_correcta": false
      },
      "42": {
        "respuesta": "A",
        "correcta": "A",
        "es_correcta": true
      },
      "43": {
        "respuesta": "B",
        "correcta": "B",
        "es_correcta": true
      },
      "44": {
        "respuesta": "C",
        "correcta": "D",
        "es_correcta": false
      },
      "45": {
        "respuesta": "A",
        "correcta": "C",
        "es_correcta": false
      },
      "46": {
        "respuesta": "B",
        "correcta": "A",
        "es_correcta": false
      },
      "47": {
        "respuesta": "C",
        "correcta": "A",
        "es_correcta": false
      },
      "48": {
        "respuesta": "C",
        "correcta": "A",
        "es_correcta": false
      },
      "49": {
        "respuesta": "A",
        "correcta": "D",
        "es_correcta": false
      },
      "50": {
        "respuesta": "D",
        "correcta": "B",
        "es_correcta": false
      },
      "51": {
        "respuesta": "A",
        "correcta": "B",
        "es_correcta": false
      },
      "52": {
        "respuesta": "A",
        "correcta": "B",
        "es_correcta": false
      },
      "53": {
        "respuesta": "B",
        "correcta": "D",
        "es_correcta": false
      },
      "54": {
        "respuesta": "D",
        "correcta": "D",
        "es_correcta": true
      },
      "55": {
        "respuesta": "A",
        "correcta": "C",
        "es_correcta": false
      },
      "56": {
        "respuesta": "C",
        "correcta": "B",
        "es_correcta": false
      },
      "57": {
        "respuesta": "C",
        "correcta": "D",
        "es_correcta": false
      },
      "58": {
        "respuesta": "B",
        "correcta": "C",
        "es_correcta": false
      },
      "59": {
        "respuesta": "D",
        "correcta": "C",
        "es_correcta": false
      },
      "60": {
        "respuesta": "A",
        "correcta": "C",
        "es_correcta": false
      },
      "61": {
        "respuesta": "A",
        "correcta": "C",
        "es_correcta": false
      },
      "62": {
        "respuesta": "C",
        "correcta": "A",
        "es_correcta": false
      },
      "63": {
        "respuesta": "D",
        "correcta": "B",
        "es_correcta": false
      },
      "64": {
        "respuesta": "B",
        "correcta": "B",
        "es_correcta": true
      },
      "65": {
        "respuesta": "B",
        "correcta": "C",
        "es_correcta": false
      },
      "66": {
        "respuesta": "C",
        "correcta": "B",
        "es_correcta": false
      }
    },
    "sociales y ciudadanas": {
      "67": {
        "respuesta": "A",
        "correcta": "C",
        "es_correcta": false
      },
      "68": {
        "respuesta": "D",
        "correcta": "A",
        "es_correcta": false
      },
      "69": {
        "respuesta": "B",
        "correcta": "B",
        "es_correcta": true
      },
      "70": {
        "respuesta": "C",
        "correcta": "A",
        "es_correcta": false
      },
      "71": {
        "respuesta": "A",
        "correcta": "A",
        "es_correcta": true
      },
      "72": {
        "respuesta": "C",
        "correcta": "B",
        "es_correcta": false
      },
      "73": {
        "respuesta": "D",
        "correcta": "B",
        "es_correcta": false
      },
      "74": {
        "respuesta": "A",
        "correcta": "B",
        "es_correcta": false
      },
      "75": {
        "respuesta": "A",
        "correcta": "C",
        "es_correcta": false
      },
      "76": {
        "respuesta": "B",
        "correcta": "B",
        "es_correcta": true
      },
      "77": {
        "respuesta": "D",
        "correcta": "B",
        "es_correcta": false
      },
      "78": {
        "respuesta": "C",
        "correcta": "A",
        "es_correcta": false
      },
      "79": {
        "respuesta": "C",
        "correcta": "D",
        "es_correcta": false
      },
      "80": {
        "respuesta": "A",
        "correcta": "B",
        "es_correcta": false
      },
      "81": {
        "respuesta": "B",
        "correcta": "B",
        "es_correcta": true
      },
      "82": {
        "respuesta": "C",
        "correcta": "B",
        "es_correcta": false
      },
      "83": {
        "respuesta": "C",
        "correcta": "D",
        "es_correcta": false
      },
      "84": {
        "respuesta": "D",
        "correcta": "A",
        "es_correcta": false
      },
      "85": {
        "respuesta": "B",
        "correcta": "C",
        "es_correcta": false
      },
      "86": {
        "respuesta": "C",
        "correcta": "A",
        "es_correcta": false
      },
      "87": {
        "respuesta": "A",
        "correcta": "C",
        "es_correcta": false
      },
      "88": {
        "respuesta": "C",
        "correcta": "B",
        "es_correcta": false
      },
      "89": {
        "respuesta": "C",
        "correcta": "C",
        "es_correcta": true
      },
      "90": {
        "respuesta": "B",
        "correcta": "B",
        "es_correcta": true
      },
      "91": {
        "respuesta": "D",
        "correcta": "C",
        "es_correcta": false
      },
      "1": {
        "respuesta": "A",
        "correcta": "B",
        "es_correcta": false
      },
      "2": {
        "respuesta": "B",
        "correcta": "A",
        "es_correcta": false
      },
      "3": {
        "respuesta": "D",
        "correcta": "B",
        "es_correcta": false
      },
      "4": {
        "respuesta": "C",
        "correcta": "B",
        "es_correcta": false
      },
      "5": {
        "respuesta": "A",
        "correcta": "D",
        "es_correcta": false
      },
      "6": {
        "respuesta": "A",
        "correcta": "C",
        "es_correcta": false
      },
      "7": {
        "respuesta": "B",
        "correcta": "D",
        "es_correcta": false
      },
      "8": {
        "respuesta": "D",
        "correcta": "C",
        "es_correcta": false
      },
      "9": {
        "respuesta": "C",
        "correcta": "D",
        "es_correcta": false
      },
      "10": {
        "respuesta": "C",
        "correcta": "D",
        "es_correcta": false
      },
      "11": {
        "respuesta": "D",
        "correcta": "C",
        "es_correcta": false
      },
      "12": {
        "respuesta": "B",
        "correcta": "C",
        "es_correcta": false
      },
      "13": {
        "respuesta": "A",
        "correcta": "B",
        "es_correcta": false
      },
      "14": {
        "respuesta": "D",
        "correcta": "D",
        "es_correcta": true
      },
      "15": {
        "respuesta": "C",
        "correcta": "D",
        "es_correcta": false
      },
      "16": {
        "respuesta": "B",
        "correcta": "D",
        "es_correcta": false
      },
      "17": {
        "respuesta": "A",
        "correcta": "C",
        "es_correcta": false
      },
      "18": {
        "respuesta": "C",
        "correcta": "D",
        "es_correcta": false
      },
      "19": {
        "respuesta": "D",
        "correcta": "A",
        "es_correcta": false
      },
      "20": {
        "respuesta": "B",
        "correcta": "D",
        "es_correcta": false
      },
      "21": {
        "respuesta": "A",
        "correcta": "D",
        "es_correcta": false
      },
      "22": {
        "respuesta": "A",
        "correcta": "B",
        "es_correcta": false
      },
      "23": {
        "respuesta": "D",
        "correcta": "A",
        "es_correcta": false
      },
      "24": {
        "respuesta": "C",
        "correcta": "C",
        "es_correcta": true
      },
      "25": {
        "respuesta": "A",
        "correcta": "C",
        "es_correcta": false
      }
    },
    "ciencias naturales": {
      "92": {
        "respuesta": "B",
        "correcta": "C",
        "es_correcta": false
      },
      "93": {
        "respuesta": "C",
        "correcta": "C",
        "es_correcta": true
      },
      "94": {
        "respuesta": "C",
        "correcta": "A",
        "es_correcta": false
      },
      "95": {
        "respuesta": "D",
        "correcta": "B",
        "es_correcta": false
      },
      "96": {
        "respuesta": "A",
        "correcta": "C",
        "es_correcta": false
      },
      "97": {
        "respuesta": "B",
        "correcta": "C",
        "es_correcta": false
      },
      "98": {
        "respuesta": "D",
        "correcta": "B",
        "es_correcta": false
      },
      "99": {
        "respuesta": "B",
        "correcta": "A",
        "es_correcta": false
      },
      "100": {
        "respuesta": "C",
        "correcta": "D",
        "es_correcta": false
      },
      "101": {
        "respuesta": "B",
        "correcta": "A",
        "es_correcta": false
      },
      "102": {
        "respuesta": "A",
        "correcta": "A",
        "es_correcta": true
      },
      "103": {
        "respuesta": "D",
        "correcta": "D",
        "es_correcta": true
      },
      "104": {
        "respuesta": "D",
        "correcta": "D",
        "es_correcta": true
      },
      "105": {
        "respuesta": "C",
        "correcta": "C",
        "es_correcta": true
      },
      "106": {
        "respuesta": "B",
        "correcta": "A",
        "es_correcta": false
      },
      "107": {
        "respuesta": "B",
        "correcta": "C",
        "es_correcta": false
      },
      "108": {
        "respuesta": "D",
        "correcta": "A",
        "es_correcta": false
      },
      "109": {
        "respuesta": "C",
        "correcta": "C",
        "es_correcta": true
      },
      "110": {
        "respuesta": "A",
        "correcta": "C",
        "es_correcta": false
      },
      "111": {
        "respuesta": "D",
        "correcta": "C",
        "es_correcta": false
      },
      "112": {
        "respuesta": "C",
        "correcta": "C",
        "es_correcta": true
      },
      "113": {
        "respuesta": "B",
        "correcta": "C",
        "es_correcta": false
      },
      "114": {
        "respuesta": "B",
        "correcta": "C",
        "es_correcta": false
      },
      "115": {
        "respuesta": "A",
        "correcta": "C",
        "es_correcta": false
      },
      "116": {
        "respuesta": "D",
        "correcta": "B",
        "es_correcta": false
      },
      "117": {
        "respuesta": "C",
        "correcta": "C",
        "es_correcta": true
      },
      "118": {
        "respuesta": "D",
        "correcta": "D",
        "es_correcta": true
      },
      "119": {
        "respuesta": "A",
        "correcta": "A",
        "es_correcta": true
      },
      "120": {
        "respuesta": "C",
        "correcta": "C",
        "es_correcta": true
      },
      "51": {
        "respuesta": "A",
        "correcta": "C",
        "es_correcta": false
      },
      "52": {
        "respuesta": "C",
        "correcta": "B",
        "es_correcta": false
      },
      "53": {
        "respuesta": "D",
        "correcta": "B",
        "es_correcta": false
      },
      "54": {
        "respuesta": "B",
        "correcta": "B",
        "es_correcta": true
      },
      "55": {
        "respuesta": "B",
        "correcta": "B",
        "es_correcta": true
      },
      "56": {
        "respuesta": "A",
        "correcta": "C",
        "es_correcta": false
      },
      "57": {
        "respuesta": "B",
        "correcta": "C",
        "es_correcta": false
      },
      "58": {
        "respuesta": "C",
        "correcta": "C",
        "es_correcta": true
      },
      "59": {
        "respuesta": "A",
        "correcta": "C",
        "es_correcta": false
      },
      "60": {
        "respuesta": "D",
        "correcta": "D",
        "es_correcta": true
      },
      "61": {
        "respuesta": "D",
        "correcta": "B",
        "es_correcta": false
      },
      "62": {
        "respuesta": "A",
        "correcta": "C",
        "es_correcta": false
      },
      "63": {
        "respuesta": "C",
        "correcta": "B",
        "es_correcta": false
      },
      "64": {
        "respuesta": "D",
        "correcta": "C",
        "es_correcta": false
      },
      "65": {
        "respuesta": "B",
        "correcta": "C",
        "es_correcta": false
      },
      "66": {
        "respuesta": "A",
        "correcta": "B",
        "es_correcta": false
      },
      "67": {
        "respuesta": "A",
        "correcta": "A",
        "es_correcta": true
      },
      "68": {
        "respuesta": "B",
        "correcta": "B",
        "es_correcta": true
      },
      "69": {
        "respuesta": "C",
        "correcta": "C",
        "es_correcta": true
      },
      "70": {
        "respuesta": "D",
        "correcta": "B",
        "es_correcta": false
      },
      "71": {
        "respuesta": "D",
        "correcta": "B",
        "es_correcta": false
      },
      "72": {
        "respuesta": "A",
        "correcta": "C",
        "es_correcta": false
      },
      "73": {
        "respuesta": "B",
        "correcta": "C",
        "es_correcta": false
      },
      "74": {
        "respuesta": "D",
        "correcta": "A",
        "es_correcta": false
      },
      "75": {
        "respuesta": "A",
        "correcta": "C",
        "es_correcta": false
      },
      "76": {
        "respuesta": "B",
        "correcta": "B",
        "es_correcta": true
      },
      "77": {
        "respuesta": "B",
        "correcta": "B",
        "es_correcta": true
      },
      "78": {
        "respuesta": "A",
        "correcta": "A",
        "es_correcta": true
      },
      "79": {
        "respuesta": "C",
        "correcta": "D",
        "es_correcta": false
      }
    },
    "inglés": {
      "80": {
        "respuesta": "B",
        "correcta": "B",
        "es_correcta": true
      },
      "81": {
        "respuesta": "A",
        "correcta": "F",
        "es_correcta": false
      },
      "82": {
        "respuesta": "C",
        "correcta": "E",
        "es_correcta": false
      },
      "83": {
        "respuesta": "D",
        "correcta": "A",
        "es_correcta": false
      },
      "84": {
        "respuesta": "G",
        "correcta": "G",
        "es_correcta": true
      },
      "85": {
        "respuesta": "A",
        "correcta": "F",
        "es_correcta": false
      },
      "86": {
        "respuesta": "C",
        "correcta": "C",
        "es_correcta": true
      },
      "87": {
        "respuesta": "D",
        "correcta": "D",
        "es_correcta": true
      },
      "88": {
        "respuesta": "F",
        "correcta": "G",
        "es_correcta": false
      },
      "89": {
        "respuesta": "H",
        "correcta": "A",
        "es_correcta": false
      },
      "90": {
        "respuesta": "A",
        "correcta": "B",
        "es_correcta": false
      },
      "91": {
        "respuesta": "C",
        "correcta": "B",
        "es_correcta": false
      },
      "92": {
        "respuesta": "B",
        "correcta": "C",
        "es_correcta": false
      },
      "93": {
        "respuesta": "B",
        "correcta": "A",
        "es_correcta": false
      },
      "94": {
        "respuesta": "B",
        "correcta": "B",
        "es_correcta": true
      },
      "95": {
        "respuesta": "C",
        "correcta": "C",
        "es_correcta": true
      },
      "96": {
        "respuesta": "A",
        "correcta": "C",
        "es_correcta": false
      },
      "97": {
        "respuesta": "B",
        "correcta": "B",
        "es_correcta": true
      },
      "98": {
        "respuesta": "B",
        "correcta": "B",
        "es_correcta": true
      },
      "99": {
        "respuesta": "A",
        "correcta": "A",
        "es_correcta": true
      },
      "100": {
        "respuesta": "B",
        "correcta": "B",
        "es_correcta": true
      },
      "101": {
        "respuesta": "A",
        "correcta": "B",
        "es_correcta": false
      },
      "102": {
        "respuesta": "C",
        "correcta": "C",
        "es_correcta": true
      },
      "103": {
        "respuesta": "B",
        "correcta": "C",
        "es_correcta": false
      },
      "104": {
        "respuesta": "B",
        "correcta": "B",
        "es_correcta": true
      },
      "105": {
        "respuesta": "A",
        "correcta": "A",
        "es_correcta": true
      },
      "106": {
        "respuesta": "B",
        "correcta": "A",
        "es_correcta": false
      },
      "107": {
        "respuesta": "C",
        "correcta": "C",
        "es_correcta": true
      },
      "108": {
        "respuesta": "B",
        "correcta": "A",
        "es_correcta": false
      },
      "109": {
        "respuesta": "A",
        "correcta": "B",
        "es_correcta": false
      },
      "110": {
        "respuesta": "A",
        "correcta": "B",
        "es_correcta": false
      },
      "111": {
        "respuesta": "B",
        "correcta": "C",
        "es_correcta": false
      },
      "112": {
        "respuesta": "C",
        "correcta": "B",
        "es_correcta": false
      },
      "113": {
        "respuesta": "B",
        "correcta": "A",
        "es_correcta": false
      },
      "114": {
        "respuesta": "A",
        "correcta": "C",
        "es_correcta": false
      },
      "115": {
        "respuesta": "D",
        "correcta": "B",
        "es_correcta": false
      },
      "116": {
        "respuesta": "B",
        "correcta": "A",
        "es_correcta": false
      },
      "117": {
        "respuesta": "C",
        "correcta": "C",
        "es_correcta": true
      },
      "118": {
        "respuesta": "A",
        "correcta": "B",
        "es_correcta": false
      },
      "119": {
        "respuesta": "A",
        "correcta": "C",
        "es_correcta": false
      },
      "120": {
        "respuesta": "B",
        "correcta": "D",
        "es_correcta": false
      },
      "121": {
        "respuesta": "C",
        "correcta": "D",
        "es_correcta": false
      },
      "122": {
        "respuesta": "C",
        "correcta": "C",
        "es_correcta": true
      },
      "123": {
        "respuesta": "D",
        "correcta": "A",
        "es_correcta": false
      },
      "124": {
        "respuesta": "B",
        "correcta": "C",
        "es_correcta": false
      },
      "125": {
        "respuesta": "B",
        "correcta": "B",
        "es_correcta": true
      },
      "126": {
        "respuesta": "C",
        "correcta": "B",
        "es_correcta": false
      },
      "127": {
        "respuesta": "A",
        "correcta": "A",
        "es_correcta": true
      },
      "128": {
        "respuesta": "A",
        "correcta": "D",
        "es_correcta": false
      },
      "129": {
        "respuesta": "D",
        "correcta": "B",
        "es_correcta": false
      },
      "130": {
        "respuesta": "C",
        "correcta": "C",
        "es_correcta": true
      },
      "131": {
        "respuesta": "A",
        "correcta": "D",
        "es_correcta": false
      },
      "132": {
        "respuesta": "B",
        "correcta": "A",
        "es_correcta": false
      },
      "133": {
        "respuesta": "C",
        "correcta": "B",
        "es_correcta": false
      },
      "134": {
        "respuesta": "A",
        "correcta": "D",
        "es_correcta": false
      }
    }
  },
  "secciones_completadas": [
    "S1",
    "S2"
  ],
  "puntaje_global": 112,
  "nivel_desempeno": "Bajo",
  "score_real": 72,
  "score_reportado": 72,
  "usa_calibracion": true
}